sbx_corpus_statistics/__init__.py
sbx_corpus_statistics/exporters.py
sbx_corpus_statistics/formatting.py
sbx_corpus_statistics/metadata.yaml
sbx_corpus_statistics/py.typed
sbx_corpus_statistics/suc_msd.py
sparv_sbx_corpus_statistics-0.1.0.dist-info/WHEEL
sparv_sbx_corpus_statistics-0.1.0.dist-info/entry_points.txt
sparv_sbx_corpus_statistics-0.1.0.dist-info/METADATA
sparv_sbx_corpus_statistics-0.1.0.dist-info/RECORD
