Metadata-Version: 2.3
Name: sparv-sbx-corpus-statistics
Version: 0.1.0
Summary: Sparv plugin to collect statistics about the created corpus
Classifier: Development Status :: 3 - Alpha
Classifier: Intended Audience :: Developers
Classifier: License :: OSI Approved :: MIT License
Classifier: Operating System :: Unix
Classifier: Operating System :: POSIX
Classifier: Operating System :: Microsoft :: Windows
Classifier: Operating System :: MacOS
Classifier: Programming Language :: Python :: 3.11
Classifier: Programming Language :: Python :: 3.12
Classifier: Programming Language :: Python :: 3.13
Classifier: Programming Language :: Python :: Implementation :: CPython
Classifier: Topic :: Utilities
Classifier: Typing :: Typed
Requires-Dist: attrs>=25.3.0
Requires-Dist: numpy>1.24.4
Requires-Dist: running-stats>=0.1.3
Requires-Dist: sparv>=5.3.1
Requires-Dist: strenum>=0.4.15
Requires-Python: >=3.11
Project-URL: Bug Tracker, https://github.com/spraakbanken/sparv-sbx-corpus-statistics/issues
Project-URL: Homepage, https://spraakbanken.gu.se
Project-URL: Repository, https://github.com/spraakbanken/sparv-sbx-corpus-statistics
